connect/__init__.py
connect/zip.py
connect_tu/__init__.py
connect_tu/zip.py
tu_connect-1.0.0.dist-info/LICENSE
tu_connect-1.0.0.dist-info/METADATA
tu_connect-1.0.0.dist-info/WHEEL
tu_connect-1.0.0.dist-info/top_level.txt
tu_connect-1.0.0.dist-info/RECORD
