Metadata-Version: 2.1
Name: tu-connect
Version: 1.0.0
Summary: Connection to TU API BRZ
Home-page: https://service.zipcode.com.br/api/help
Author: Rogerio Domingues
Author-email: rogerio.domingues@transunion.com
License: UNKNOWN
Platform: UNKNOWN
Classifier: Programming Language :: Python :: 3
Classifier: License :: OSI Approved :: MIT License
Classifier: Operating System :: OS Independent
Requires-Python: >=3.6
